vhcalc/__init__.py
vhcalc/app.py
vhcalc/models/__init__.py
vhcalc/models/imghash_function.py
vhcalc/models/metadata.py
vhcalc/models/url.py
vhcalc/services/__init__.py
vhcalc/services/imghashes.py
vhcalc/services/reader_frames.py
vhcalc/tools/__init__.py
vhcalc/tools/chunk.py
vhcalc/tools/docenum.py
vhcalc/tools/forked/__init__.py
vhcalc/tools/forked/click_default_group.py
vhcalc/tools/forked/click_path.py
vhcalc/tools/forked/imageio_ffmpeg_io.py
vhcalc/tools/imghash.py
vhcalc/tools/progress_bar.py
vhcalc/tools/version_extended_informations.py
vhcalc-0.8.0.dist-info/LICENSE
vhcalc-0.8.0.dist-info/METADATA
vhcalc-0.8.0.dist-info/WHEEL
vhcalc-0.8.0.dist-info/entry_points.txt
vhcalc-0.8.0.dist-info/RECORD
