Metadata-Version: 2.1
Name: vhcalc
Version: 0.8.0
Summary: It's a client-side library that implements a custom algorithm for extracting video hashes (fingerprints) from any video source.
Home-page: https://github.com/yoyonel/vhcalc
License: MIT
Author: Lionel Atty
Author-email: yoyonel@hotmail.com
Requires-Python: >=3.9,<4.0
Classifier: License :: OSI Approved :: MIT License
Classifier: Programming Language :: Python :: 3
Classifier: Programming Language :: Python :: 3.9
Classifier: Programming Language :: Python :: 3.10
Classifier: Programming Language :: Python :: 3.11
Classifier: Programming Language :: Python :: 3.12
Requires-Dist: Distance (>=0.1.3,<0.2.0)
Requires-Dist: ImageHash (>=4.3.1,<5.0.0)
Requires-Dist: Pillow (>=9.1.1)
Requires-Dist: bitstring (>=4.2.3,<5.0.0)
Requires-Dist: click (>=8.1.7,<9.0.0)
Requires-Dist: click-pathlib (>=2020.3.13,<2021.0.0)
Requires-Dist: colorama (>=0.4.6,<0.5.0)
Requires-Dist: imageio-ffmpeg (>=0.5.1,<0.6.0)
Requires-Dist: loguru (>=0.7.2,<0.8.0)
Requires-Dist: numpy (>=2.0.2,<3.0.0)
Requires-Dist: pymediainfo (>=6.1.0)
Requires-Dist: rich (>=13.8.0,<14.0.0)
Requires-Dist: rich-click (>=1.8.3,<2.0.0)
Requires-Dist: typeguard (>=4.3.0,<5.0.0)
Requires-Dist: types-setuptools (>=74.0.0.20240830,<75.0.0.0)
Project-URL: Repository, https://github.com/yoyonel/vhcalc
